gbr_distributions/Binomialdistribution.py
gbr_distributions/Gaussiandistribution.py
gbr_distributions/Generaldistribution.py
gbr_distributions/__init__.py
gbr_distributions-0.1.dist-info/DESCRIPTION.rst
gbr_distributions-0.1.dist-info/METADATA
gbr_distributions-0.1.dist-info/RECORD
gbr_distributions-0.1.dist-info/WHEEL
gbr_distributions-0.1.dist-info/metadata.json
gbr_distributions-0.1.dist-info/top_level.txt
