Metadata-Version: 2.0
Name: gbr-distributions
Version: 0.1
Summary: Gaussian distributions
Home-page: UNKNOWN
Author: ritesh_vesalapu
Author-email: riteshvesalapu@gmail.com
License: UNKNOWN
Platform: UNKNOWN
